autopilotml/.DS_Store
autopilotml/__init__.py
autopilotml/autopilotml.py
autopilotml/cli.py
autopilotml/streamlit_ui.py
autopilotml/data_loading/__init__.py
autopilotml/data_loading/database_operation.py
autopilotml/data_loading/reader.py
autopilotml/dataset/.DS_Store
autopilotml/dataset/Power_Output.csv
autopilotml/dataset/data.csv
autopilotml/dataset/titanic_train.csv
autopilotml/feature_selection/__init__.py
autopilotml/feature_selection/feature_engineering.py
autopilotml/feature_selection/feature_selection.py
autopilotml/model_building/__init__.py
autopilotml/model_building/models.py
autopilotml/model_tuning/__init__.py
autopilotml/model_tuning/tuning.py
autopilotml/preprocessing/__init__.py
autopilotml/preprocessing/imputation.py
autopilotml/preprocessing/outlier.py
autopilotml/research/autopilotml_examples.ipynb
autopilotml/research/test.ipynb
autopilotml/research/.ipynb_checkpoints/autopilotml_examples-checkpoint.ipynb
autopilotml/research/.ipynb_checkpoints/stage_1-checkpoint.ipynb
autopilotml/research/.ipynb_checkpoints/test-checkpoint.ipynb
autopilotml/scaling/__init__.py
autopilotml/scaling/scaler.py
autopilotml/transformation/__init__.py
autopilotml/transformation/transform.py
autopilotml-1.0.14.dist-info/LICENSE
autopilotml-1.0.14.dist-info/METADATA
autopilotml-1.0.14.dist-info/WHEEL
autopilotml-1.0.14.dist-info/entry_points.txt
autopilotml-1.0.14.dist-info/top_level.txt
autopilotml-1.0.14.dist-info/RECORD
